tablemate-0.1.0.dev2.data/data/EGG-INFO/LICENSE
tablemate-0.1.0.dev2.data/data/EGG-INFO/README.md
tablemate-0.1.0.dev2.dist-info/top_level.txt
tablemate-0.1.0.dev2.dist-info/RECORD
tablemate-0.1.0.dev2.dist-info/WHEEL
tablemate-0.1.0.dev2.dist-info/metadata.json
tablemate-0.1.0.dev2.dist-info/entry_points.txt
tablemate-0.1.0.dev2.dist-info/DESCRIPTION.rst
tablemate-0.1.0.dev2.dist-info/METADATA
tablemate/_compat.py
tablemate/__main__.py
tablemate/config.py
tablemate/__init__.py
tablemate/commands/help.py
tablemate/commands/__init__.py
tablemate/util/dclick.py
tablemate/util/__init__.py
