Metadata-Version: 2.0
Name: tablemate
Version: 0.1.0.dev2
Summary: Prettify your tabular data, either on the command line or in Python code.
Home-page: https://github.com/jhermann/tablemate
Author: Jürgen Hermann
Author-email: jh@web.de
License: Apache 2.0
Keywords: hosted.by.github,tables,console,color,unicode,csv,prettyprint,prettify
Platform: UNKNOWN
Classifier: Development Status :: 3 - Alpha
Classifier: Environment :: Console
Classifier: Intended Audience :: Developers
Classifier: Intended Audience :: System Administrators
Classifier: License :: OSI Approved :: Apache Software License
Classifier: Operating System :: OS Independent
Classifier: Programming Language :: Python :: 2
Classifier: Programming Language :: Python :: 2.7
Classifier: Programming Language :: Python :: 3
Classifier: Programming Language :: Python :: 3.4
Classifier: Topic :: Software Development :: Libraries :: Python Modules
Classifier: Topic :: Software Development :: User Interfaces
Classifier: Topic :: Text Processing :: Filters
Classifier: Topic :: Utilities
Requires-Dist: click (>=3.3,<4)
Requires-Dist: colorama
Requires-Dist: configobj
